wengine/__init__.py
wengine/main.py
wengine/functions/__init__.py
wengine/functions/api_functions.py
wengine/functions/general_functions.py
wengine/functions/start_functions.py
wengine/functions/functions_test/__init__.py
wengine/functions/functions_test/start_functions_test.py
wengine/tests/__init__.py
wengine/tests/api_tests.py
wengine/tests/blank_test.py
wengine/tests/get_status_test.py
wengine/tests/main_test.py
wengine/tests/test_objects.py
wengine-0.1.0.dist-info/METADATA
wengine-0.1.0.dist-info/WHEEL
wengine-0.1.0.dist-info/top_level.txt
wengine-0.1.0.dist-info/RECORD
