Metadata-Version: 2.1
Name: wengine
Version: 0.1.0
Summary: WEngine - оператор работы с weighing_platform
Home-page: UNKNOWN
Author: Arthur
Author-email: ksmdrmvstchny@gmail.com
License: UNKNOWN
Platform: UNKNOWN
Requires-Dist: whikoperator
Requires-Dist: weighting-platform
Requires-Dist: qodex-skud-bus
Requires-Dist: gravityRecorder
Requires-Dist: ghik-frame
Requires-Dist: weightsplitter
Requires-Dist: wsqluse
